{
  "name": "penguinctl",
  "full_name": "penguinctl",
  "tap": null,
  "oldname": null,
  "oldnames": [],
  "aliases": [],
  "versioned_formulae": [],
  "desc": "Penguin CLI",
  "license": null,
  "homepage": "https://github.com/vmware-tanzu-learning/penguinctl",
  "versions": {
    "stable": "0.6.4",
    "head": null,
    "bottle": false
  },
  "urls": {
    "stable": {
      "url": "https://github.com/vmware-tanzu-learning/penguinctl-release/releases/download/v0.6.4/penguinctl_v0.6.4_darwin_amd64.tar.gz",
      "tag": null,
      "revision": null,
      "checksum": "5f7e29d568e990f475e65308e4a2f3aa7f17078bd7d93082c09c713f82a06493"
    }
  },
  "revision": 0,
  "version_scheme": 0,
  "bottle": {},
  "keg_only": false,
  "keg_only_reason": null,
  "options": [],
  "build_dependencies": [],
  "dependencies": [],
  "test_dependencies": [],
  "recommended_dependencies": [],
  "optional_dependencies": [],
  "uses_from_macos": [],
  "requirements": [],
  "conflicts_with": [],
  "conflicts_with_reasons": [],
  "link_overwrite": [],
  "caveats": null,
  "installed": [],
  "linked_keg": null,
  "pinned": false,
  "outdated": false,
  "deprecated": false,
  "deprecation_date": null,
  "deprecation_reason": null,
  "disabled": false,
  "disable_date": null,
  "disable_reason": null,
  "service": null,
  "tap_git_head": null,
  "ruby_source_path": null,
  "ruby_source_checksum": {
    "sha256": "c6db0c09f632d7340e3864dc79c61c8369108c7c3ea7ef4180331166b0972084"
  }
}
